infoman/__init__.py
infoman/cli/README.md
infoman/cli/__init__.py
infoman/cli/scaffold.py
infoman/cli/commands/__init__.py
infoman/cli/commands/init.py
infoman/cli/templates/Makefile.template
infoman/cli/templates/app/__init__.py.template
infoman/cli/templates/app/app.py.template
infoman/cli/templates/app/models_base.py.template
infoman/cli/templates/app/models_entity_init.py.template
infoman/cli/templates/app/models_schemas_init.py.template
infoman/cli/templates/app/repository_init.py.template
infoman/cli/templates/app/routers_init.py.template
infoman/cli/templates/app/services_init.py.template
infoman/cli/templates/app/static_index.html.template
infoman/cli/templates/app/static_main.js.template
infoman/cli/templates/app/static_style.css.template
infoman/cli/templates/app/utils_init.py.template
infoman/cli/templates/config/.env.dev.template
infoman/cli/templates/config/.env.prod.template
infoman/cli/templates/config/README.md.template
infoman/cli/templates/docker/.dockerignore.template
infoman/cli/templates/docker/Dockerfile.template
infoman/cli/templates/docker/README.md.template
infoman/cli/templates/docker/docker-compose.yml.template
infoman/cli/templates/docker/mysql_custom.cnf.template
infoman/cli/templates/docker/mysql_init.sql.template
infoman/cli/templates/project/.env.example.template
infoman/cli/templates/project/.gitignore.template
infoman/cli/templates/project/Makefile.template
infoman/cli/templates/project/README.md.template
infoman/cli/templates/project/deploy.sh.template
infoman/cli/templates/project/main.py.template
infoman/cli/templates/project/manage.sh.template
infoman/cli/templates/project/pyproject.toml.template
infoman/cli/templates/project/service.sh.template
infoman/config/__init__.py
infoman/config/base.py
infoman/config/db_cache.py
infoman/config/db_relation.py
infoman/config/db_vector.py
infoman/config/jwt.py
infoman/config/llm.py
infoman/config/log.py
infoman/config/mq.py
infoman/config/settings.py
infoman/llm/__init__.py
infomankit-0.3.22.dist-info/METADATA
infomankit-0.3.22.dist-info/WHEEL
infomankit-0.3.22.dist-info/entry_points.txt
infomankit-0.3.22.dist-info/RECORD
