Metadata-Version: 2.4
Name: infomankit
Version: 0.3.22
Summary: Infoman base library - A comprehensive toolkit for modern Python applications with dual ORM support
Project-URL: Homepage, https://github.com/infoman-lib/infoman-pykit
Project-URL: Documentation, https://github.com/infoman-lib/infoman-pykit
Project-URL: Repository, https://github.com/infoman-lib/infoman-pykit.git
Project-URL: Issues, https://github.com/infoman-lib/infoman-pykit/issues
Project-URL: Changelog, https://github.com/infoman-lib/infoman-pykit/blob/main/CHANGELOG.md
Author-email: Louis <louishwh@gmail.com>
Maintainer-email: Louis <louishwh@gmail.com>
License: MIT
Keywords: async,database,fastapi,llm,toolkit
Classifier: Development Status :: 4 - Beta
Classifier: Framework :: AsyncIO
Classifier: Framework :: FastAPI
Classifier: Intended Audience :: Developers
Classifier: License :: OSI Approved :: MIT License
Classifier: Programming Language :: Python :: 3
Classifier: Programming Language :: Python :: 3.11
Classifier: Programming Language :: Python :: 3.12
Classifier: Topic :: Internet :: WWW/HTTP :: HTTP Servers
Classifier: Topic :: Software Development :: Libraries :: Python Modules
Requires-Python: >=3.11
Requires-Dist: aiohttp~=3.13.2
Requires-Dist: click~=8.1.0
Requires-Dist: cryptography~=46.0.3
Requires-Dist: dotenv==0.9.9
Requires-Dist: httpx~=0.28.1
Requires-Dist: loguru~=0.7.0
Requires-Dist: psutil~=7.1.3
Requires-Dist: pydantic-settings>=2.12.0
Requires-Dist: pydantic~=2.12.0
Requires-Dist: pyjwt~=2.10.0
Requires-Dist: pyyaml~=6.0.2
Provides-Extra: cache
Requires-Dist: fastapi-cache2~=0.2.2; extra == 'cache'
Requires-Dist: redis[hiredis]~=7.1.0; extra == 'cache'
Provides-Extra: database
Requires-Dist: aiosqlite~=0.22.0; extra == 'database'
Requires-Dist: asyncmy~=0.2.10; extra == 'database'
Requires-Dist: asyncpg~=0.31.0; extra == 'database'
Requires-Dist: tortoise-orm~=0.25.2; extra == 'database'
Provides-Extra: database-pro
Requires-Dist: aiosqlite~=0.22.0; extra == 'database-pro'
Requires-Dist: alembic~=1.14.0; extra == 'database-pro'
Requires-Dist: asyncmy~=0.2.10; extra == 'database-pro'
Requires-Dist: asyncpg~=0.31.0; extra == 'database-pro'
Requires-Dist: sqlalchemy[asyncio]~=2.0.36; extra == 'database-pro'
Provides-Extra: dev
Requires-Dist: mypy>=1.8.0; extra == 'dev'
Requires-Dist: pre-commit>=3.6.0; extra == 'dev'
Requires-Dist: pytest-asyncio>=0.23.0; extra == 'dev'
Requires-Dist: pytest-cov>=4.0.0; extra == 'dev'
Requires-Dist: pytest>=8.0.0; extra == 'dev'
Requires-Dist: ruff>=0.14.10; extra == 'dev'
Provides-Extra: docs
Requires-Dist: mkdocs-material~=9.0.0; extra == 'docs'
Requires-Dist: mkdocstrings[python]>=0.24.0; extra == 'docs'
Requires-Dist: mkdocs~=1.6.1; extra == 'docs'
Provides-Extra: full
Requires-Dist: aiofiles~=25.1.0; extra == 'full'
Requires-Dist: aiosqlite~=0.22.0; extra == 'full'
Requires-Dist: asyncmy~=0.2.10; extra == 'full'
Requires-Dist: asyncpg~=0.31.0; extra == 'full'
Requires-Dist: fastapi-cache2~=0.2.2; extra == 'full'
Requires-Dist: fastapi~=0.127.0; extra == 'full'
Requires-Dist: granian~=2.6.0; extra == 'full'
Requires-Dist: jinja2~=3.1.6; extra == 'full'
Requires-Dist: litellm~=1.75.0; extra == 'full'
Requires-Dist: nats-py~=2.10.0; extra == 'full'
Requires-Dist: orjson~=3.11.5; extra == 'full'
Requires-Dist: prometheus-client~=0.23.1; extra == 'full'
Requires-Dist: prometheus-fastapi-instrumentator~=7.1.0; extra == 'full'
Requires-Dist: python-multipart>=0.0.20; extra == 'full'
Requires-Dist: qdrant-client~=1.16.2; extra == 'full'
Requires-Dist: redis[hiredis]~=7.1.0; extra == 'full'
Requires-Dist: tortoise-orm~=0.25.2; extra == 'full'
Provides-Extra: full-pro
Requires-Dist: aiofiles~=25.1.0; extra == 'full-pro'
Requires-Dist: aiosqlite~=0.22.0; extra == 'full-pro'
Requires-Dist: alembic~=1.14.0; extra == 'full-pro'
Requires-Dist: asyncmy~=0.2.10; extra == 'full-pro'
Requires-Dist: asyncpg~=0.31.0; extra == 'full-pro'
Requires-Dist: fastapi-cache2~=0.2.2; extra == 'full-pro'
Requires-Dist: fastapi~=0.127.0; extra == 'full-pro'
Requires-Dist: granian~=2.6.0; extra == 'full-pro'
Requires-Dist: jinja2~=3.1.6; extra == 'full-pro'
Requires-Dist: litellm~=1.75.0; extra == 'full-pro'
Requires-Dist: nats-py~=2.10.0; extra == 'full-pro'
Requires-Dist: orjson~=3.11.5; extra == 'full-pro'
Requires-Dist: prometheus-client~=0.23.1; extra == 'full-pro'
Requires-Dist: prometheus-fastapi-instrumentator~=7.1.0; extra == 'full-pro'
Requires-Dist: python-multipart>=0.0.20; extra == 'full-pro'
Requires-Dist: qdrant-client~=1.16.2; extra == 'full-pro'
Requires-Dist: redis[hiredis]~=7.1.0; extra == 'full-pro'
Requires-Dist: sqlalchemy[asyncio]~=2.0.36; extra == 'full-pro'
Provides-Extra: llm
Requires-Dist: litellm~=1.75.0; extra == 'llm'
Provides-Extra: messaging
Requires-Dist: nats-py~=2.10.0; extra == 'messaging'
Provides-Extra: test
Requires-Dist: factory-boy>=3.3.0; extra == 'test'
Requires-Dist: httpx>=0.25.0; extra == 'test'
Requires-Dist: mypy>=1.8.0; extra == 'test'
Requires-Dist: pre-commit>=3.6.0; extra == 'test'
Requires-Dist: pytest-asyncio>=0.23.0; extra == 'test'
Requires-Dist: pytest-benchmark>=4.0.0; extra == 'test'
Requires-Dist: pytest-cov>=4.0.0; extra == 'test'
Requires-Dist: pytest>=8.0.0; extra == 'test'
Requires-Dist: ruff>=0.14.10; extra == 'test'
Provides-Extra: vector
Requires-Dist: qdrant-client~=1.16.2; extra == 'vector'
Provides-Extra: web
Requires-Dist: aiofiles~=25.1.0; extra == 'web'
Requires-Dist: fastapi~=0.127.0; extra == 'web'
Requires-Dist: granian~=2.6.0; extra == 'web'
Requires-Dist: jinja2~=3.1.6; extra == 'web'
Requires-Dist: orjson~=3.11.5; extra == 'web'
Requires-Dist: prometheus-client~=0.23.1; extra == 'web'
Requires-Dist: prometheus-fastapi-instrumentator~=7.1.0; extra == 'web'
Requires-Dist: python-multipart>=0.0.20; extra == 'web'
Provides-Extra: web-basic
Requires-Dist: aiofiles~=25.1.0; extra == 'web-basic'
Requires-Dist: aiosqlite~=0.22.0; extra == 'web-basic'
Requires-Dist: asyncmy~=0.2.10; extra == 'web-basic'
Requires-Dist: asyncpg~=0.31.0; extra == 'web-basic'
Requires-Dist: fastapi~=0.127.0; extra == 'web-basic'
Requires-Dist: granian~=2.6.0; extra == 'web-basic'
Requires-Dist: jinja2~=3.1.6; extra == 'web-basic'
Requires-Dist: orjson~=3.11.5; extra == 'web-basic'
Requires-Dist: prometheus-client~=0.23.1; extra == 'web-basic'
Requires-Dist: prometheus-fastapi-instrumentator~=7.1.0; extra == 'web-basic'
Requires-Dist: python-multipart>=0.0.20; extra == 'web-basic'
Requires-Dist: tortoise-orm~=0.25.2; extra == 'web-basic'
Provides-Extra: web-cache
Requires-Dist: aiofiles~=25.1.0; extra == 'web-cache'
Requires-Dist: aiosqlite~=0.22.0; extra == 'web-cache'
Requires-Dist: asyncmy~=0.2.10; extra == 'web-cache'
Requires-Dist: asyncpg~=0.31.0; extra == 'web-cache'
Requires-Dist: fastapi-cache2~=0.2.2; extra == 'web-cache'
Requires-Dist: fastapi~=0.127.0; extra == 'web-cache'
Requires-Dist: granian~=2.6.0; extra == 'web-cache'
Requires-Dist: jinja2~=3.1.6; extra == 'web-cache'
Requires-Dist: orjson~=3.11.5; extra == 'web-cache'
Requires-Dist: prometheus-client~=0.23.1; extra == 'web-cache'
Requires-Dist: prometheus-fastapi-instrumentator~=7.1.0; extra == 'web-cache'
Requires-Dist: python-multipart>=0.0.20; extra == 'web-cache'
Requires-Dist: redis[hiredis]~=7.1.0; extra == 'web-cache'
Requires-Dist: tortoise-orm~=0.25.2; extra == 'web-cache'
Provides-Extra: web-full
Requires-Dist: aiofiles~=25.1.0; extra == 'web-full'
Requires-Dist: aiosqlite~=0.22.0; extra == 'web-full'
Requires-Dist: asyncmy~=0.2.10; extra == 'web-full'
Requires-Dist: asyncpg~=0.31.0; extra == 'web-full'
Requires-Dist: fastapi-cache2~=0.2.2; extra == 'web-full'
Requires-Dist: fastapi~=0.127.0; extra == 'web-full'
Requires-Dist: granian~=2.6.0; extra == 'web-full'
Requires-Dist: jinja2~=3.1.6; extra == 'web-full'
Requires-Dist: nats-py~=2.10.0; extra == 'web-full'
Requires-Dist: orjson~=3.11.5; extra == 'web-full'
Requires-Dist: prometheus-client~=0.23.1; extra == 'web-full'
Requires-Dist: prometheus-fastapi-instrumentator~=7.1.0; extra == 'web-full'
Requires-Dist: python-multipart>=0.0.20; extra == 'web-full'
Requires-Dist: qdrant-client~=1.16.2; extra == 'web-full'
Requires-Dist: redis[hiredis]~=7.1.0; extra == 'web-full'
Requires-Dist: tortoise-orm~=0.25.2; extra == 'web-full'
Provides-Extra: web-service
Requires-Dist: aiofiles~=25.1.0; extra == 'web-service'
Requires-Dist: aiosqlite~=0.22.0; extra == 'web-service'
Requires-Dist: asyncmy~=0.2.10; extra == 'web-service'
Requires-Dist: asyncpg~=0.31.0; extra == 'web-service'
Requires-Dist: fastapi-cache2~=0.2.2; extra == 'web-service'
Requires-Dist: fastapi~=0.127.0; extra == 'web-service'
Requires-Dist: granian~=2.6.0; extra == 'web-service'
Requires-Dist: jinja2~=3.1.6; extra == 'web-service'
Requires-Dist: orjson~=3.11.5; extra == 'web-service'
Requires-Dist: prometheus-client~=0.23.1; extra == 'web-service'
Requires-Dist: prometheus-fastapi-instrumentator~=7.1.0; extra == 'web-service'
Requires-Dist: python-multipart>=0.0.20; extra == 'web-service'
Requires-Dist: redis[hiredis]~=7.1.0; extra == 'web-service'
Requires-Dist: tortoise-orm~=0.25.2; extra == 'web-service'
